MANIFEST.in
README.rst
setup.py
aliyun_python_sdk_openanalytics.egg-info/PKG-INFO
aliyun_python_sdk_openanalytics.egg-info/SOURCES.txt
aliyun_python_sdk_openanalytics.egg-info/dependency_links.txt
aliyun_python_sdk_openanalytics.egg-info/requires.txt
aliyun_python_sdk_openanalytics.egg-info/top_level.txt
aliyunsdkopenanalytics/__init__.py
aliyunsdkopenanalytics/request/__init__.py
aliyunsdkopenanalytics/request/v20180301/CloseProductAccountRequest.py
aliyunsdkopenanalytics/request/v20180301/DescribeRegionListRequest.py
aliyunsdkopenanalytics/request/v20180301/GetAllowIPRequest.py
aliyunsdkopenanalytics/request/v20180301/GetEndPointByDomainRequest.py
aliyunsdkopenanalytics/request/v20180301/GetProductStatusRequest.py
aliyunsdkopenanalytics/request/v20180301/GetRegionStatusRequest.py
aliyunsdkopenanalytics/request/v20180301/OpenProductAccountRequest.py
aliyunsdkopenanalytics/request/v20180301/QueryEndPointListRequest.py
aliyunsdkopenanalytics/request/v20180301/SetAllowIPRequest.py
aliyunsdkopenanalytics/request/v20180301/__init__.py